{
  "actions/navigate/enter_galaxy": [
    "Opening the galaxy console.",
    "Bringing up the galaxy controls.",
    "Galaxy console coming up.",
    "Opening simulation settings.",
    "Showing the galaxy console.",
    "Loading the orbit controls.",
    "Opening the universe console.",
    "Galaxy controls online.",
    "Bringing the simulation panel forward.",
    "Opening the playground console.",
    "Simulation controls ready.",
    "Launching the galaxy console.",
    "Pulling up the galaxy dashboard.",
    "Opening orbital command.",
    "Galaxy panel restored.",
    "Showing the simulation console.",
    "Universe controls coming up.",
    "Opening the orbital interface.",
    "Galaxy console ready.",
    "Bringing up the big cosmic control panel."
  ],
  "actions/navigate/exit_galaxy": [
    "Closing the galaxy console.",
    "Hiding the galaxy controls.",
    "Galaxy console closed.",
    "Closing simulation settings.",
    "Putting the galaxy console away.",
    "Exiting the orbit controls.",
    "Closing the universe console.",
    "Galaxy controls dismissed.",
    "Returning from the simulation panel.",
    "Closing the playground console.",
    "Simulation controls hidden.",
    "Leaving the galaxy console.",
    "Putting away the galaxy dashboard.",
    "Closing orbital command.",
    "Galaxy panel dismissed.",
    "Closing the simulation console.",
    "Universe controls hidden.",
    "Exiting the orbital interface.",
    "Galaxy console packed away.",
    "Closing the cosmic control panel."
  ],
  "actions/simulation/add_body": [
    "Adding it to the simulation.",
    "Placing it in the universe.",
    "Spawning it on the screen.",
    "Adding that body now.",
    "Bringing it into the scene.",
    "Putting it into orbit.",
    "Adding it to the playground.",
    "Dropping it into the simulation.",
    "Creating its place in the system.",
    "Adding the object to space.",
    "Bringing that planet in.",
    "Placing the body at the center view.",
    "Adding it to the active system.",
    "Launching it into the scene.",
    "Putting that world on screen.",
    "Adding the celestial body.",
    "Spawning the requested object.",
    "Injecting it into the universe.",
    "Adding it to the cosmic mess.",
    "Done, throwing it into space responsibly."
  ],
  "actions/simulation/remove_body": [
    "Removing it from the simulation.",
    "Taking it out of the scene.",
    "Deleting it from the universe.",
    "Removing that body now.",
    "Clearing it from the screen.",
    "Taking it out of orbit.",
    "Removing it from the playground.",
    "Despawning the object.",
    "Removing it from the active system.",
    "Clearing that planet.",
    "Taking that world away.",
    "Removing the celestial body.",
    "Deleting the requested object.",
    "Pulling it out of the simulation.",
    "Removing it from space.",
    "Clearing it from the universe view.",
    "Taking the body off screen.",
    "Removing it from the cosmic setup.",
    "Object removed.",
    "Done, one less thing floating around."
  ],
  "actions/galaxy/center_anchor": [
    "Centering the anchor.",
    "Focusing the anchor body.",
    "Moving to the anchor.",
    "Centering the main body.",
    "Finding the orbit anchor.",
    "Bringing the anchor into view.",
    "Focusing the center body.",
    "Recentering on the anchor.",
    "Locking view onto the anchor.",
    "Showing the anchor body.",
    "Camera centered on the anchor.",
    "Moving the view to the anchor.",
    "Centering orbital focus.",
    "Anchor body coming into view.",
    "Repositioning toward the anchor.",
    "Focusing the simulation anchor.",
    "Centering the system core.",
    "Snapping view to the anchor.",
    "Anchor located.",
    "Centering the boss body."
  ],
  "actions/galaxy/reset_orbits": [
    "Resetting the orbits.",
    "Rebuilding the orbital paths.",
    "Restoring the trajectories.",
    "Resetting orbital motion.",
    "Recalculating the paths.",
    "Fixing the orbit layout.",
    "Restoring stable orbits.",
    "Resetting the revolutions.",
    "Refreshing the trajectory setup.",
    "Rebuilding the simulation paths.",
    "Orbit reset complete.",
    "Recalculating orbital behavior.",
    "Putting the orbits back in order.",
    "Resetting the system motion.",
    "Restoring the orbital configuration.",
    "Cleaning up the orbit logic.",
    "Re-aligning the trajectories.",
    "Resetting the cosmic dance.",
    "Orbits restored.",
    "Fixing the space spaghetti."
  ],
  "actions/galaxy/clear_trails": [
    "Clearing the trails.",
    "Erasing trajectory lines.",
    "Removing orbit trails.",
    "Clearing path history.",
    "Wiping the trails.",
    "Removing the trail lines.",
    "Clearing the simulation traces.",
    "Erasing the orbital paths.",
    "Cleaning up the screen.",
    "Removing trajectory history.",
    "Trails cleared.",
    "Clearing all motion traces.",
    "Wiping the orbit history.",
    "Removing the path lines.",
    "Clearing the visual trails.",
    "Deleting the trajectory traces.",
    "Cleaning the universe view.",
    "Clearing the orbital scribbles.",
    "Path history removed.",
    "Trails gone. The universe looks less chaotic now."
  ]
}